setup.cfg
setup.py
xmlsquash/__init__.py
xmlsquash.egg-info/PKG-INFO
xmlsquash.egg-info/SOURCES.txt
xmlsquash.egg-info/dependency_links.txt
xmlsquash.egg-info/not-zip-safe
xmlsquash.egg-info/top_level.txt
xmlsquash/tests/__init__.py
xmlsquash/tests/test_complex.py
xmlsquash/tests/test_duplicate.py
xmlsquash/tests/test_flat.py
xmlsquash/tests/test_normal.py