Metadata-Version: 1.0
Name: xmlsquash
Version: 0.1.1dev
Summary: XML 2 Dict converter
Home-page: http://bfaludi.com
Author: Bence Faludi
Author-email: hello@bfaludi.com
License: GPL
Platform: UNKNOWN
